tsfaker/__init__.py
tsfaker/exceptions.py
tsfaker/main.py
tsfaker/tstype.py
tsfaker/generator/__init__.py
tsfaker/generator/column.py
tsfaker/generator/foreign_key.py
tsfaker/generator/table.py
tsfaker/io/__init__.py
tsfaker/io/io_arguments.py
tsfaker/io/resources.py
tsfaker/io/schema.py
tsfaker/io/utils.py
tsfaker-0.14.dist-info/LICENSE
tsfaker-0.14.dist-info/METADATA
tsfaker-0.14.dist-info/WHEEL
tsfaker-0.14.dist-info/entry_points.txt
tsfaker-0.14.dist-info/top_level.txt
tsfaker-0.14.dist-info/RECORD
