Metadata-Version: 2.1
Name: tsfaker
Version: 0.14
Summary: Generate fake data conforming to a Table Schema
Home-page: https://gitlab.com/healthdatahub/tsfaker/
Author: Pierre-Alain Jachiet - DREES
Author-email: ld-lab-github@sante.gouv.fr
License: MPL-2.0
Platform: UNKNOWN
Requires-Python: ~=3.5
Requires-Dist: click
Requires-Dist: numpy
Requires-Dist: pandas
Requires-Dist: rstr
Requires-Dist: tableschema
Requires-Dist: dsfaker
Provides-Extra: dev
Requires-Dist: sphinx ; extra == 'dev'
Requires-Dist: pytest ; extra == 'dev'
Requires-Dist: pytest-timeout ; extra == 'dev'
Requires-Dist: goodtables ; extra == 'dev'
Requires-Dist: tableschema (>=1.5.4) ; extra == 'dev'
